sdk/__init__.py
sdk/sdk.py
sdk/models/__init__.py
sdk/models/operations/__init__.py
sdk/models/operations/mutation_products_create.py
sdk/models/operations/mutation_products_update.py
sdk/models/operations/mutation_seats_redeemseat.py
sdk/models/operations/mutation_seats_releaseseat.py
sdk/models/operations/mutation_seats_requestseat.py
sdk/models/operations/mutation_seats_reserveseat.py
sdk/models/operations/mutation_seats_updateuoccupant.py
sdk/models/operations/mutation_subscriptions_createsubscription.py
sdk/models/operations/mutation_subscriptions_updatesubscription.py
sdk/models/operations/query_products_all.py
sdk/models/operations/query_products_byid.py
sdk/models/operations/query_seats_byid.py
sdk/models/operations/query_seats_bysubscription.py
sdk/models/operations/query_seats_userseat.py
sdk/models/operations/query_subscriptions_all.py
sdk/models/operations/query_subscriptions_byid.py
sdk/utils/__init__.py
sdk/utils/retries.py
sdk/utils/utils.py
bouncer_client_sdk-0.1.0.dist-info/METADATA
bouncer_client_sdk-0.1.0.dist-info/WHEEL
bouncer_client_sdk-0.1.0.dist-info/top_level.txt
bouncer_client_sdk-0.1.0.dist-info/RECORD
