Metadata-Version: 2.1
Name: bouncer-client-sdk
Version: 0.1.0
Summary: Python Client SDK Generated by Speakeasy
Home-page: UNKNOWN
Author: Speakeasy
License: UNKNOWN
Platform: UNKNOWN
Requires-Python: >=3.9
Requires-Dist: certifi (==2022.12.07)
Requires-Dist: charset-normalizer (==2.1.1)
Requires-Dist: dacite (==1.6.0)
Requires-Dist: dataclasses-json-speakeasy (==0.5.8)
Requires-Dist: idna (==3.3)
Requires-Dist: marshmallow (==3.17.1)
Requires-Dist: marshmallow-enum (==1.5.1)
Requires-Dist: mypy-extensions (==0.4.3)
Requires-Dist: packaging (==21.3)
Requires-Dist: pyparsing (==3.0.9)
Requires-Dist: python-dateutil (==2.8.2)
Requires-Dist: requests (==2.28.1)
Requires-Dist: six (==1.16.0)
Requires-Dist: typing-inspect (==0.8.0)
Requires-Dist: typing-extensions (==4.3.0)
Requires-Dist: urllib3 (==1.26.12)
